reno_structured_output/__init__.py
reno_structured_output/cli.py
reno_structured_output/collect_notes.py
reno_structured_output/py.typed
reno_structured_output-0.6.1.dist-info/METADATA
reno_structured_output-0.6.1.dist-info/WHEEL
reno_structured_output-0.6.1.dist-info/entry_points.txt
reno_structured_output-0.6.1.dist-info/RECORD
