Metadata-Version: 2.4
Name: reno-structured-output
Version: 0.6.1
Summary: Add your description here
Author-email: Jan Scholz <jan.scholz@gmail.com>
Requires-Python: >=3.9
Requires-Dist: pyyaml>=6.0.2
Requires-Dist: reno>=4.0.0
